hwpack_calculator/__init__.py
hwpack_calculator/calculator.py
hwpack_calculator-0.1.0.dist-info/licenses/LICENSE
hwpack_calculator-0.1.0.dist-info/METADATA
hwpack_calculator-0.1.0.dist-info/WHEEL
hwpack_calculator-0.1.0.dist-info/top_level.txt
hwpack_calculator-0.1.0.dist-info/RECORD
