Metadata-Version: 2.4
Name: hwpack_calculator
Version: 0.1.0
Summary: A simple calculator package for basic arithmetic operations
Author: heartedwings
License: MIT
Project-URL: Homepage, https://github.com/heartedwings/hwpack_calculator
Requires-Python: >=3.6
License-File: LICENSE
Dynamic: license-file
